banduppy/__init__.py
banduppy/unfolding.py
banduppy/BasicFunctions/__init__.py
banduppy/BasicFunctions/general_functions.py
banduppy/BasicFunctions/general_plot_functions.py
banduppy/Utilities/EBS_plot.py
banduppy/Utilities/EBS_properties.py
banduppy/Utilities/__init__.py
banduppy/Utilities/folding_degree_plot.py
banduppy/src/__init__.py
banduppy/src/folding.py
banduppy/src/folding_properties.py
banduppy/src/unfolding.py
banduppy-0.3.4.dist-info/LICENSE
banduppy-0.3.4.dist-info/METADATA
banduppy-0.3.4.dist-info/WHEEL
banduppy-0.3.4.dist-info/top_level.txt
banduppy-0.3.4.dist-info/RECORD
