Metadata-Version: 2.1
Name: banduppy
Version: 0.3.4
Summary: BandUPpy: Python interface of the BandUP code
Home-page: https://github.com/band-unfolding/banduppy
Author: Stepan S. Tsirkin
Author-email: stepan.tsirkin@ehu.eus
Maintainer: Badal Mondal
Maintainer-email: badalmondal.chembgc@gmail.com
Classifier: Programming Language :: Python :: 3
Classifier: License :: OSI Approved :: GNU General Public License v3 (GPLv3)
Classifier: Operating System :: OS Independent
License-File: LICENSE
Requires-Dist: numpy
Requires-Dist: scipy >=1.0
Requires-Dist: matplotlib
Requires-Dist: irrep >=1.9.3
